eskodesk/__init__.py
eskodesk/client.py
eskodesk/exceptions.py
eskodesk-0.1.0.dist-info/METADATA
eskodesk-0.1.0.dist-info/WHEEL
eskodesk-0.1.0.dist-info/top_level.txt
eskodesk-0.1.0.dist-info/RECORD
