Metadata-Version: 2.1
Name: eskodesk
Version: 0.1.0
Summary: Python client for the Eskodesk API
Home-page: UNKNOWN
Author: Eskolare Negócios Digitais Ltda
Author-email: vitor.f@eskolare.com.br
License: UNKNOWN
Platform: UNKNOWN
Classifier: Development Status :: 4 - Beta
Classifier: Environment :: Web Environment
Classifier: Intended Audience :: Developers
Classifier: License :: Other/Proprietary License
Classifier: Operating System :: OS Independent
Classifier: Programming Language :: Python
Classifier: Programming Language :: Python :: 3
Classifier: Programming Language :: Python :: 3.5
Classifier: Programming Language :: Python :: 3.6
Classifier: Programming Language :: Python :: 3.7
Classifier: Programming Language :: Python :: 3.8
Classifier: Programming Language :: Python :: 3.9
Classifier: Topic :: Software Development
Requires-Python: >=3.5
Requires-Dist: requests (<2.26,>=2.14.0)
